{
  "SolutionPath": "D:\\01 - Grags\\Visual Studio\\Spellvain",
  "OptionStates": {
    "Code Files": true,
    "Config Files": false,
    "Designer Files": false,
    "Include Other Files": false,
    "Json Files": false,
    "Project Files": false,
    "Resource Files": false,
    "Distill Active Projects Only": false,
    "Distill Project (Bible Mode)": false,
    "Distill Unused": false,
    "Exclude Project Settings": false,
    "Remove Comments": true,
    "Sanitize Files (Recommended)": true,
    "Squish Designer Files": false,
    "Copy To Clipboard": true,
    "Create File": false,
    "Include Message": true,
    "Include Project Structure": true,
    "Open File On Completion": false,
    "Open Folder On Completion": false,
    "Show Per-File Token Counts": true
  },
  "CheckedFiles": [
    "Character Editor\\Character Editor\\Classes\\AbilityDisplayWrapper.vb",
    "Character Editor\\Character Editor\\Classes\\BlankExpandableObjectConverter.vb",
    "Character Editor\\Character Editor\\Classes\\NumericUpDownEditor.vb",
    "Character Editor\\Character Editor\\Classes\\PropertyGridTypeConverters.vb",
    "Character Editor\\Character Editor\\Forms\\User Controls\\ucSlider\\AnimationPropertyGridWrapper.vb",
    "Character Editor\\Character Editor\\Forms\\User Controls\\ucSlider\\SliderEditor.vb",
    "Character Editor\\Character Editor\\Forms\\User Controls\\ucSlider\\ucSlider.vb",
    "Character Editor\\Character Editor\\Forms\\User Controls\\ucAbilityAnimationEditor.vb",
    "Character Editor\\Character Editor\\Forms\\User Controls\\ucAnimationEditor.vb",
    "Character Editor\\Character Editor\\Forms\\frmAbilityEditor.vb",
    "Character Editor\\Character Editor\\Forms\\frmMain.vb",
    "Spellvain.Data\\Class Modules\\Abilities\\AbilityData.vb",
    "Spellvain.Data\\Class Modules\\Abilities\\AbilityRegistry.vb",
    "Spellvain.Data\\Class Modules\\Animation\\Battle Animations\\AttackAnimationData.vb",
    "Spellvain.Data\\Class Modules\\Animation\\Battle Animations\\BreathAnimationData.vb",
    "Spellvain.Data\\Class Modules\\Animation\\Battle Animations\\DeathAnimationData.vb",
    "Spellvain.Data\\Class Modules\\Animation\\Battle Animations\\ImpactAnimationData.vb",
    "Spellvain.Data\\Class Modules\\Animation\\Battle Animations\\ImpactReactionData.vb",
    "Spellvain.Data\\Class Modules\\Animation\\Battle Animations\\JoltAnimationData.vb",
    "Spellvain.Data\\Class Modules\\Animation\\Battle Animations\\MagicAnimationData.vb",
    "Spellvain.Data\\Class Modules\\Animation\\Battle Animations\\MeleeAnimationData.vb",
    "Spellvain.Data\\Class Modules\\Animation\\Battle Animations\\PreCastAnimationData.vb",
    "Spellvain.Data\\Class Modules\\Animation\\Battle Animations\\RotationAnimationData.vb",
    "Spellvain.Data\\Class Modules\\Animation\\Battle Animations\\SquishAnimationData.vb",
    "Spellvain.Data\\Class Modules\\Animation\\Battle Animations\\TakeHitAnimationData.vb",
    "Spellvain.Data\\Class Modules\\Animation\\AnimationEnums.vb",
    "Spellvain.Data\\Class Modules\\Animation\\AnimationSet.vb",
    "Spellvain.Data\\Class Modules\\Animation\\CharacterAnimator.vb",
    "Spellvain.Data\\Class Modules\\Atmospherics\\VFXManager.vb",
    "Spellvain.Data\\Class Modules\\Battle\\BattleCharacter.vb",
    "Spellvain.Data\\Class Modules\\Characters\\CharacterData.vb",
    "Spellvain.Data\\Class Modules\\Characters\\CharacterRegistry.vb",
    "Spellvain.Data\\Class Modules\\System\\Enums.vb",
    "Spellvain.Data\\Class Modules\\System\\GameDataManager.vb"
  ],
  "ExpandedNodes": [
    "Area Editor",
    "Area Editor\\Controls",
    "Area Editor\\Forms",
    "Character Editor",
    "Character Editor\\Classes",
    "Character Editor\\Forms",
    "Character Editor\\Forms\\User Controls",
    "Scene Manager",
    "Spellvain.Data",
    "Spellvain.Data\\Class Modules",
    "Spellvain.Data\\Class Modules\\Abilities",
    "Spellvain.Data\\Class Modules\\Animation",
    "Spellvain.Data\\Class Modules\\Animation\\Battle Animations",
    "Spellvain.Data\\Class Modules\\Atmospherics",
    "Spellvain.Data\\Class Modules\\Battle",
    "Spellvain.Data\\Class Modules\\Characters",
    "Spellvain.Data\\Class Modules\\Scenes",
    "Spellvain.Data\\Class Modules\\System",
    "Spellvain.Data\\Class Modules\\UI",
    "Spellvain",
    "Spellvain\\Data",
    "Spellvain\\Data\\Classes",
    "Spellvain\\Data\\Classes\\AI",
    "Spellvain\\Data\\Custom Controls",
    "Spellvain\\Data\\Forms",
    "UI Editor"
  ]
}